ryomath/init.py
ryomath/multiply.py
ryomath-0.1.0.dist-info/METADATA
ryomath-0.1.0.dist-info/WHEEL
ryomath-0.1.0.dist-info/top_level.txt
ryomath-0.1.0.dist-info/RECORD
